MANIFEST.in
README.md
librflxlang.gpr
pyproject.toml
setup.py
RecordFlux_parser.egg-info/PKG-INFO
RecordFlux_parser.egg-info/SOURCES.txt
RecordFlux_parser.egg-info/dependency_links.txt
RecordFlux_parser.egg-info/top_level.txt
gnatcoll-bindings/gmp/gmp_support.c
gnatcoll-bindings/gmp/gnatcoll-gmp-integers-io.adb
gnatcoll-bindings/gmp/gnatcoll-gmp-integers-io.ads
gnatcoll-bindings/gmp/gnatcoll-gmp-integers-misc.adb
gnatcoll-bindings/gmp/gnatcoll-gmp-integers-misc.ads
gnatcoll-bindings/gmp/gnatcoll-gmp-integers-number_theoretic.adb
gnatcoll-bindings/gmp/gnatcoll-gmp-integers-number_theoretic.ads
gnatcoll-bindings/gmp/gnatcoll-gmp-integers-random.adb
gnatcoll-bindings/gmp/gnatcoll-gmp-integers-random.ads
gnatcoll-bindings/gmp/gnatcoll-gmp-integers-root_extraction.adb
gnatcoll-bindings/gmp/gnatcoll-gmp-integers-root_extraction.ads
gnatcoll-bindings/gmp/gnatcoll-gmp-integers.adb
gnatcoll-bindings/gmp/gnatcoll-gmp-integers.ads
gnatcoll-bindings/gmp/gnatcoll-gmp-lib.ads
gnatcoll-bindings/gmp/gnatcoll-gmp-mpz_even_p.c
gnatcoll-bindings/gmp/gnatcoll-gmp-mpz_odd_p.c
gnatcoll-bindings/gmp/gnatcoll-gmp-mpz_sign.c
gnatcoll-bindings/gmp/gnatcoll-gmp-random_state.adb
gnatcoll-bindings/gmp/gnatcoll-gmp-random_state.ads
gnatcoll-bindings/gmp/gnatcoll-gmp.ads
gnatcoll-bindings/gmp/gnatcoll_gmp.gpr
gnatcoll-bindings/gmp/examples/gmp_examples.gpr
gnatcoll-bindings/gmp/examples/isprime.adb
gnatcoll-bindings/gmp/examples/square_triangular_numbers.adb
gnatcoll-bindings/iconv/gnatcoll-iconv.adb
gnatcoll-bindings/iconv/gnatcoll-iconv.ads
gnatcoll-bindings/iconv/gnatcoll_iconv.gpr
gnatcoll-bindings/iconv/iconv_support.c
langkit/support/langkit_support-adalog-abstract_relation.adb
langkit/support/langkit_support-adalog-abstract_relation.ads
langkit/support/langkit_support-adalog-debug.adb
langkit/support/langkit_support-adalog-debug.ads
langkit/support/langkit_support-adalog-eq_same.adb
langkit/support/langkit_support-adalog-eq_same.ads
langkit/support/langkit_support-adalog-logic_ref.adb
langkit/support/langkit_support-adalog-logic_ref.ads
langkit/support/langkit_support-adalog-logic_var.ads
langkit/support/langkit_support-adalog-main_support.adb
