Metadata-Version: 2.1
Name: RecordFlux-parser
Version: 0.11.0
Summary: RecordFlux parser
Home-page: https://github.com/Componolit/RecordFlux-parser
Author: Alexander Senier
Author-email: senier@componolit.com
License: AGPL-3.0
Classifier: Development Status :: 5 - Production/Stable
Classifier: Environment :: Console
Classifier: License :: OSI Approved :: GNU Affero General Public License v3
Classifier: Operating System :: POSIX :: Linux
Classifier: Programming Language :: Ada
Classifier: Programming Language :: Python :: 3 :: Only
Classifier: Programming Language :: Python :: 3
Classifier: Programming Language :: Python :: 3.7
Classifier: Programming Language :: Python :: 3.8
Classifier: Programming Language :: Python :: 3.9
Classifier: Topic :: Communications
Classifier: Topic :: Security
Classifier: Topic :: Software Development :: Build Tools
Classifier: Topic :: Software Development :: Code Generators
Classifier: Topic :: System :: Networking
Requires-Python: >=3.7
